smartpredict/__init__.py
smartpredict/base.py
smartpredict/ensemble_methods.py
smartpredict/explainability.py
smartpredict/feature_engineering.py
smartpredict/hyperparameter_tuning.py
smartpredict/model_assessment.py
smartpredict/model_selection.py
smartpredict/supervised.py
smartpredict/utils.py
smartpredict-0.8.1.dist-info/METADATA
smartpredict-0.8.1.dist-info/WHEEL
smartpredict-0.8.1.dist-info/top_level.txt
smartpredict-0.8.1.dist-info/RECORD
