Metadata-Version: 2.4
Name: smartpredict
Version: 0.8.1
Summary: An advanced machine learning library for effortless model training, evaluation, and selection.
Home-page: https://github.com/SubaashNair/SmartPredict
Author: Subashanan Nair
Author-email: subaashnair12@gmail.com
Classifier: Programming Language :: Python :: 3
Classifier: License :: OSI Approved :: MIT License
Classifier: Operating System :: OS Independent
Requires-Python: >=3.6
Requires-Dist: scikit-learn
Requires-Dist: numpy
Requires-Dist: pandas
Requires-Dist: shap
Requires-Dist: optuna
Requires-Dist: xgboost
Requires-Dist: lightgbm
Requires-Dist: catboost
Requires-Dist: tensorflow
Requires-Dist: torch
Dynamic: author
Dynamic: author-email
Dynamic: classifier
Dynamic: description
Dynamic: description-content-type
Dynamic: home-page
Dynamic: requires-dist
Dynamic: requires-python
Dynamic: summary
